genomeplot/__init__.py
genomeplot/genomeplot.py
genomeplot/prerolled/__init__.py
genomeplot/prerolled/anophelesgambiae.py
genomeplot/prerolled/data/anophelesgambiae.txt
genomeplot/prerolled/data/homosapiens.txt
genomeplot/prerolled/data/plasmodiumfalciparum.txt
genomeplot/prerolled/homosapiens.py
genomeplot/prerolled/plasmodiumfalciparum.py
genomeplot/prerolled/util.py
LICENSE
genomeplot-0.4.0.dist-info/LICENSE
genomeplot-0.4.0.dist-info/WHEEL
genomeplot-0.4.0.dist-info/METADATA
genomeplot-0.4.0.dist-info/RECORD
